docs/conf.py
docs/notebooks/01_demo_EWMA.py
docs/notebooks/02_Synchronize_data_streams.py
docs/notebooks/03_ohlc_temperature.py
docs/notebooks/04_The_three_steps_workflow.py
docs/notebooks/05_reconstructing_the_light_curve_of_stars.py
docs/notebooks/06_Online_Linear_Regression.py
docs/notebooks/07_Online_Time_Series_Prediction.py
docs/notebooks/08_Online_learning_in_non_stationary_environments.py
wax/VERSION
wax/__init__.py
wax/accessors.py
wax/accessors_test.py
wax/compile.py
wax/encode.py
wax/encode_test.py
wax/format.py
wax/format_test.py
wax/predicate.py
wax/stateful.py
wax/stateful_test.py
wax/stream.py
wax/stream_test.py
wax/testing.py
wax/transform.py
wax/unroll.py
wax/unroll_test.py
wax/utils.py
wax/datasets/__init__.py
wax/datasets/generate_temperature_data.py
wax/datasets/generate_temperature_data_test.py
wax/gym/__init__.py
wax/gym/agent.py
wax/gym/agent_test.py
wax/gym/entity.py
wax/gym/env.py
wax/gym/env_test.py
wax/gym/gym_unroll.py
wax/gym/haiku_agent.py
wax/gym/haiku_env.py
wax/gym/haiku_env_test.py
wax/gym/callbacks/__init__.py
wax/gym/callbacks/callbacks.py
wax/gym/callbacks/callbacks_test.py
wax/gym/callbacks/progressbar.py
wax/gym/callbacks/record.py
wax/gym/callbacks/stop.py
wax/modules/__init__.py
wax/modules/apply_mask.py
wax/modules/apply_mask_test.py
wax/modules/arma.py
wax/modules/arma_test.py
wax/modules/buffer.py
wax/modules/buffer_test.py
wax/modules/counter.py
wax/modules/counter_test.py
wax/modules/diff.py
wax/modules/diff_test.py
wax/modules/ewma.py
wax/modules/ewma_test.py
wax/modules/ewmcov.py
wax/modules/ewmcov_test.py
wax/modules/ewmvar.py
wax/modules/ewmvar_test.py
wax/modules/ffill.py
wax/modules/ffill_test.py
wax/modules/fill_nan_inf.py
wax/modules/fill_nan_inf_test.py
wax/modules/func_optimizer.py
wax/modules/func_optimizer_test.py
wax/modules/gym_feedback.py
wax/modules/gym_feedback_test.py
wax/modules/has_changed.py
wax/modules/lag.py
wax/modules/lag_test.py
wax/modules/mask_mean.py
wax/modules/mask_mean_test.py
wax_ml-0.6.4.dist-info/AUTHORS
wax_ml-0.6.4.dist-info/LICENSE
wax_ml-0.6.4.dist-info/LICENSE_SHORT
wax_ml-0.6.4.dist-info/METADATA
wax_ml-0.6.4.dist-info/WHEEL
wax_ml-0.6.4.dist-info/top_level.txt
wax_ml-0.6.4.dist-info/RECORD
