Metadata-Version: 2.1
Name: wax-ml
Version: 0.6.4
Summary: A Python library for machine-learning and feedback loops on streaming data
Home-page: https://github.com/eserie/wax-ml
Author: WAX-ML Authors
Author-email: eserie@gmail.com
License: Apache
Keywords: time series,machine learning,optimization,optimal control,online learning,reinforcement learning
Classifier: Development Status :: 3 - Alpha
Classifier: License :: OSI Approved :: Apache Software License
Classifier: Programming Language :: Python :: 3
Classifier: Operating System :: OS Independent
Classifier: Intended Audience :: Science/Research
Classifier: Topic :: Scientific/Engineering
License-File: LICENSE
License-File: LICENSE_SHORT
License-File: AUTHORS
Requires-Dist: numpy
Requires-Dist: pandas
Requires-Dist: seaborn
Requires-Dist: xarray (>=0.18.0)
Requires-Dist: scikit-learn
Requires-Dist: tqdm
Requires-Dist: jaxlib
Requires-Dist: jax
Requires-Dist: dm-haiku (>=0.0.4)
Provides-Extra: complete
Requires-Dist: optax ; extra == 'complete'
Requires-Dist: plotnine ; extra == 'complete'
Requires-Dist: pyarrow ; extra == 'complete'
Requires-Dist: pooch ; extra == 'complete'
Requires-Dist: graphviz ; extra == 'complete'
Requires-Dist: numba ; extra == 'complete'
Requires-Dist: mypy ; extra == 'complete'
Requires-Dist: ipykernel ; extra == 'complete'
Requires-Dist: ipywidgets ; extra == 'complete'
Requires-Dist: nbconvert ; extra == 'complete'
Requires-Dist: pytest ; extra == 'complete'
Requires-Dist: pytest-cov ; extra == 'complete'
Requires-Dist: pytest-xdist ; extra == 'complete'
Requires-Dist: pytest-benchmark ; extra == 'complete'
Requires-Dist: flaky ; extra == 'complete'
Requires-Dist: coverage ; extra == 'complete'
Requires-Dist: flake8 ; extra == 'complete'
Requires-Dist: autopep8 ; extra == 'complete'
Requires-Dist: autoflake ; extra == 'complete'
Requires-Dist: black ; extra == 'complete'
Requires-Dist: isort (>=5.3.0) ; extra == 'complete'
Requires-Dist: jupytext ; extra == 'complete'
Requires-Dist: papermill ; extra == 'complete'
Requires-Dist: line-profiler ; extra == 'complete'
Provides-Extra: dev
Requires-Dist: mypy ; extra == 'dev'
Requires-Dist: ipykernel ; extra == 'dev'
Requires-Dist: ipywidgets ; extra == 'dev'
Requires-Dist: nbconvert ; extra == 'dev'
Requires-Dist: pytest ; extra == 'dev'
Requires-Dist: pytest-cov ; extra == 'dev'
Requires-Dist: pytest-xdist ; extra == 'dev'
Requires-Dist: pytest-benchmark ; extra == 'dev'
Requires-Dist: flaky ; extra == 'dev'
Requires-Dist: coverage ; extra == 'dev'
Requires-Dist: flake8 ; extra == 'dev'
Requires-Dist: autopep8 ; extra == 'dev'
Requires-Dist: autoflake ; extra == 'dev'
Requires-Dist: black ; extra == 'dev'
Requires-Dist: isort (>=5.3.0) ; extra == 'dev'
Requires-Dist: jupytext ; extra == 'dev'
Requires-Dist: papermill ; extra == 'dev'
Requires-Dist: line-profiler ; extra == 'dev'
Provides-Extra: docs
Requires-Dist: optax ; extra == 'docs'
Requires-Dist: plotnine ; extra == 'docs'
Requires-Dist: pyarrow ; extra == 'docs'
Requires-Dist: pooch ; extra == 'docs'
Requires-Dist: graphviz ; extra == 'docs'
Requires-Dist: numba ; extra == 'docs'
Requires-Dist: mypy ; extra == 'docs'
Requires-Dist: ipykernel ; extra == 'docs'
Requires-Dist: ipywidgets ; extra == 'docs'
Requires-Dist: nbconvert ; extra == 'docs'
Requires-Dist: pytest ; extra == 'docs'
Requires-Dist: pytest-cov ; extra == 'docs'
Requires-Dist: pytest-xdist ; extra == 'docs'
Requires-Dist: pytest-benchmark ; extra == 'docs'
Requires-Dist: flaky ; extra == 'docs'
Requires-Dist: coverage ; extra == 'docs'
Requires-Dist: flake8 ; extra == 'docs'
Requires-Dist: autopep8 ; extra == 'docs'
Requires-Dist: autoflake ; extra == 'docs'
Requires-Dist: black ; extra == 'docs'
Requires-Dist: isort (>=5.3.0) ; extra == 'docs'
Requires-Dist: jupytext ; extra == 'docs'
Requires-Dist: papermill ; extra == 'docs'
Requires-Dist: line-profiler ; extra == 'docs'
Requires-Dist: sphinx ; extra == 'docs'
Requires-Dist: sphinxcontrib-napoleon ; extra == 'docs'
Requires-Dist: sphinx-rtd-theme ; extra == 'docs'
Requires-Dist: sphinx-autodoc-typehints ; extra == 'docs'
Requires-Dist: sphinx-autosummary-accessors ; extra == 'docs'
Requires-Dist: ipython ; extra == 'docs'
Requires-Dist: jupyter-client ; extra == 'docs'
Requires-Dist: jupyter-sphinx ; extra == 'docs'
Requires-Dist: myst-nb ; extra == 'docs'
Requires-Dist: nbsphinx ; extra == 'docs'
Requires-Dist: scanpydoc ; extra == 'docs'
Requires-Dist: matplotlib ; extra == 'docs'
Requires-Dist: sklearn ; extra == 'docs'
Provides-Extra: optional
Requires-Dist: optax ; extra == 'optional'
Requires-Dist: plotnine ; extra == 'optional'
Requires-Dist: pyarrow ; extra == 'optional'
Requires-Dist: pooch ; extra == 'optional'
Requires-Dist: graphviz ; extra == 'optional'
Requires-Dist: numba ; extra == 'optional'
